{
  "collapse-filter": false,
  "search": "",
  "showTags": true,
  "showAttachments": false,
  "hideUnresolved": false,
  "showOrphans": true,
  "collapse-color-groups": false,
  "colorGroups": [
    {
      "query": "path:C++",
      "color": {
        "a": 1,
        "rgb": 15793956
      }
    },
    {
      "query": "path:Mellpomenna",
      "color": {
        "a": 1,
        "rgb": 785972
      }
    },
    {
      "query": "path:Общее",
      "color": {
        "a": 1,
        "rgb": 975305
      }
    },
    {
      "query": "path:Windows",
      "color": {
        "a": 1,
        "rgb": 1714687
      }
    },
    {
      "query": "path:GPU",
      "color": {
        "a": 1,
        "rgb": 5373446
      }
    },
    {
      "query": "path:GPU/DirectX12",
      "color": {
        "a": 1,
        "rgb": 9109421
      }
    },
    {
      "query": "path:Алгоритмы",
      "color": {
        "a": 1,
        "rgb": 16201736
      }
    },
    {
      "query": "tag:I#ntel",
      "color": {
        "a": 1,
        "rgb": 2661104
      }
    },
    {
      "query": "tag:#AMD",
      "color": {
        "a": 1,
        "rgb": 12656415
      }
    },
    {
      "query": "tag:#CPU",
      "color": {
        "a": 1,
        "rgb": 16198583
      }
    },
    {
      "query": "tag:#Nvidia",
      "color": {
        "a": 1,
        "rgb": 3244587
      }
    },
    {
      "query": "tag:#Microsoft",
      "color": {
        "a": 1,
        "rgb": 65459
      }
    },
    {
      "query": "tag:#Security",
      "color": {
        "a": 1,
        "rgb": 15991195
      }
    },
    {
      "query": "tag:#Процессоры",
      "color": {
        "a": 1,
        "rgb": 16711744
      }
    },
    {
      "query": "path:GameDev",
      "color": {
        "a": 1,
        "rgb": 16028427
      }
    },
    {
      "query": "path:Asembler",
      "color": {
        "a": 1,
        "rgb": 8847605
      }
    },
    {
      "query": "tag:#TODO",
      "color": {
        "a": 1,
        "rgb": 16711680
      }
    }
  ],
  "collapse-display": false,
  "showArrow": true,
  "textFadeMultiplier": -2,
  "nodeSizeMultiplier": 1.0953125,
  "lineSizeMultiplier": 3.8515625,
  "collapse-forces": false,
  "centerStrength": 0.744791666666667,
  "repelStrength": 15.7291666666667,
  "linkStrength": 1,
  "linkDistance": 356,
  "scale": 0.50876188557927,
  "close": false
}